ChefScript/__init__.py
ChefScript/__main__.py
ChefScript/interpreter.py
ChefScript/parser.py
ChefScript/utils.py
pychef/__init__.py
pychef/ingredient.py
pychef/recipe.py
pychef/utils.py
ChefScript-0.1.1.dist-info/LICENSE
ChefScript-0.1.1.dist-info/METADATA
ChefScript-0.1.1.dist-info/WHEEL
ChefScript-0.1.1.dist-info/entry_points.txt
ChefScript-0.1.1.dist-info/top_level.txt
ChefScript-0.1.1.dist-info/RECORD
