Metadata-Version: 2.1
Name: ChefScript
Version: 0.1.1
Summary: An esolang for storing, creating and using recipes
Author-email: Yuanhao 'Nyoeghau' Chen <nyoeghau@nyoeghau.com>
License: # Copyright 2022 Yuanhao Chen
Project-URL: homepage, https://github.com/edward-martyr/ChefScript
Project-URL: repository, https://github.com/edward-martyr/ChefScript
Keywords: ChefScript,recipe,cooking,esolang,esoteric
Classifier: Programming Language :: Python :: 3.10
Classifier: Programming Language :: Python :: 3.11
Classifier: Development Status :: 1 - Planning
Classifier: License :: OSI Approved :: BSD License
Classifier: Operating System :: OS Independent
Requires-Python: >=3.10
License-File: LICENSE
Requires-Dist: numpy
Requires-Dist: PyParsing (~=3.0)
Requires-Dist: quantities (==0.13.0)
Requires-Dist: regex
Provides-Extra: lint
Requires-Dist: black (==22.6.0) ; extra == 'lint'
Requires-Dist: flake8 (==4.0.1) ; extra == 'lint'
Requires-Dist: isort (==5.10.1) ; extra == 'lint'
Requires-Dist: mypy (==0.971) ; extra == 'lint'
